int_rev
str_rev/intrevers
